README.md
setup.cfg
setup.py
fizzbuzz/__init__.py
fizzbuzz/fizzbuzz.py
fizzbuzzy.egg-info/PKG-INFO
fizzbuzzy.egg-info/SOURCES.txt
fizzbuzzy.egg-info/dependency_links.txt
fizzbuzzy.egg-info/top_level.txt