Metadata-Version: 2.1
Name: fizzbuzzy
Version: 0.0.1
Summary: Python package which prints Fizz, Buzz, FizzBuzz divisible by 3 and 5 and both
Home-page: https://github.com/santhoshse7en/FizzBuzz
Author: M Santhosh Kumar
Author-email: santhoshse7en@gmail.com
License: UNKNOWN
Platform: UNKNOWN
Classifier: Programming Language :: Python :: 3
Classifier: License :: OSI Approved :: MIT License
Classifier: Operating System :: OS Independent
